charmed_analytics_ci/__init__.py
charmed_analytics_ci/git_client.py
charmed_analytics_ci/logger.py
charmed_analytics_ci/main.py
charmed_analytics_ci/rock_ci_metadata_models.py
charmed_analytics_ci/rock_integrator.py
charmed_analytics_ci/rock_metadata_handler.py
charmed_analytics_ci/templates/__init__.py
charmed_analytics_ci/templates/pr_body.md.j2
charmed_analytics_ci-1.2.0.dist-info/LICENSE
charmed_analytics_ci-1.2.0.dist-info/METADATA
charmed_analytics_ci-1.2.0.dist-info/WHEEL
charmed_analytics_ci-1.2.0.dist-info/entry_points.txt
charmed_analytics_ci-1.2.0.dist-info/RECORD
