Metadata-Version: 2.3
Name: charmed-analytics-ci
Version: 1.2.0
Summary: A CLI tool for automating CI tasks across Charmed Operator repositories
License: Apache-2.0
Keywords: charm,ci,rock,automation,github,charmed-kubeflow
Author: Charmed Kubeflow
Requires-Python: >=3.12,<4.0
Classifier: Intended Audience :: Developers
Classifier: License :: OSI Approved :: Apache Software License
Classifier: Operating System :: OS Independent
Classifier: Programming Language :: Python :: 3
Classifier: Programming Language :: Python :: 3.12
Classifier: Programming Language :: Python :: 3.13
Classifier: Topic :: Software Development :: Build Tools
Requires-Dist: GitPython (>=3.1.44,<4.0.0)
Requires-Dist: Jinja2 (>=3.1.6,<4.0.0)
Requires-Dist: PyGithub (>=2.6.1,<3.0.0)
Requires-Dist: PyYAML (>=6.0.2,<7.0.0)
Requires-Dist: click (>=8.2.1,<9.0.0)
Requires-Dist: jsonpath-ng (>=1.7.0,<2.0.0)
Requires-Dist: pydantic (>=2.11.7,<3.0.0)
Requires-Dist: ruamel.yaml (>=0.18.14,<0.19.0)
Project-URL: Homepage, https://github.com/canonical/charmed-analytics-ci
Project-URL: Repository, https://github.com/canonical/charmed-analytics-ci
